KnuthB.cpython-38-darwin.so
KnuthB-0.0.1.dist-info/METADATA
KnuthB-0.0.1.dist-info/WHEEL
KnuthB-0.0.1.dist-info/top_level.txt
KnuthB-0.0.1.dist-info/RECORD
