Metadata-Version: 2.1
Name: KnuthB
Version: 0.0.1
Summary: Knuth B Shuffle Algorithm
Home-page: UNKNOWN
Author: Robert Sharp
Author-email: webmaster@sharpdesigndigital.com
License: UNKNOWN
Keywords: Shuffle,Knuth B Algorithm
Platform: UNKNOWN
Classifier: Development Status :: 3 - Alpha
Requires-Python: >=3.6
